RoadBuilder/__init__.py
RoadBuilder/__main__.py
RoadBuilder/build_road_gui.py
RoadBuilder/clothoids_window.py
RoadBuilder/get_road_element_dict.py
RoadBuilder/intersection.py
RoadBuilder/parking_area.py
RoadBuilder/preview_window.py
RoadBuilder/python_writer_reader.py
RoadBuilder/select_line_style.py
RoadBuilder/starter.py
RoadBuilder/traffic_island.py
RoadBuilder/xml_writer_reader.py
RoadBuilder-0.0.8.dist-info/METADATA
RoadBuilder-0.0.8.dist-info/WHEEL
RoadBuilder-0.0.8.dist-info/entry_points.txt
RoadBuilder-0.0.8.dist-info/top_level.txt
RoadBuilder-0.0.8.dist-info/RECORD
