Metadata-Version: 2.1
Name: RoadBuilder
Version: 0.0.8
Summary: Road builder
Home-page: https://github.com/LukasLange28/RoadBuilder
Author: Lukas Lange
Author-email: UNKNOWN
License: GPL 3.0
Keywords: xml vehicles track interface
Platform: UNKNOWN
Requires-Dist: PyQt5
Requires-Dist: track-generator
